\section{Appendix - Studiu de caz}

In continuare, voi exemplica structura unui fisier clasa cu un exemplu.

Codul Java este urmatorul:

\begin{lstlisting}[language=Java]
public class Main {
    public static void main(String[] args) {
        System.out.println("project1 - hello world");
        foo();
    }

    public static void foo() {
        System.out.println("project1 - foo()");
    }
}
\end{lstlisting}

Compilatorul folosit este \texttt{openjdk-11}. Clasa a fost utilizata
folosind utilitarul \texttt{javap} \cite{javap}, care este de asemenea inclus
in pachetul \texttt{openjdk-11}.

In primul rand, tabela de constante:

\begin{lstlisting}
Constant pool:
   #1 = Methodref          #8.#18         // java/lang/Object."<init>":()V
   #2 = Fieldref           #19.#20        // java/lang/System.out:Ljava/io/PrintStream;
   #3 = String             #21            // project1 - hello world
   #4 = Methodref          #22.#23        // java/io/PrintStream.println:(Ljava/lang/String;)V
   #5 = Methodref          #7.#24         // Main.foo:()V
   #6 = String             #25            // project1 - foo()
   #7 = Class              #26            // Main
   #8 = Class              #27            // java/lang/Object
   #9 = Utf8               <init>
  #10 = Utf8               ()V
  #11 = Utf8               Code
  #12 = Utf8               LineNumberTable
  #13 = Utf8               main
  #14 = Utf8               ([Ljava/lang/String;)V
  #15 = Utf8               foo
  #16 = Utf8               SourceFile
  #17 = Utf8               Main.java
  #18 = NameAndType        #9:#10         // "<init>":()V
  #19 = Class              #28            // java/lang/System
  #20 = NameAndType        #29:#30        // out:Ljava/io/PrintStream;
  #21 = Utf8               project1 - hello world
  #22 = Class              #31            // java/io/PrintStream
  #23 = NameAndType        #32:#33        // println:(Ljava/lang/String;)V
  #24 = NameAndType        #15:#10        // foo:()V
  #25 = Utf8               project1 - foo()
  #26 = Utf8               Main
  #27 = Utf8               java/lang/Object
  #28 = Utf8               java/lang/System
  #29 = Utf8               out
  #30 = Utf8               Ljava/io/PrintStream;
  #31 = Utf8               java/io/PrintStream
  #32 = Utf8               println
  #33 = Utf8               (Ljava/lang/String;)V
\end{lstlisting}

In acest format, namespace-urile imbricate sunt reprezentate prin
\texttt{/}.

Informatii despre clasa:

\begin{lstlisting}
Classfile Main.class
  Last modified May 28, 2018; size 520 bytes
  MD5 checksum 248b729dfe4b4bc8da895944d30fdc28
  Compiled from "Main.java"
public class Main
  minor version: 0
  major version: 55
  flags: (0x0021) ACC_PUBLIC, ACC_SUPER
  this_class: #7                          // Main
  super_class: #8                         // java/lang/Object
  interfaces: 0, fields: 0, methods: 3, attributes: 1
\end{lstlisting}

Constructorul clasei:

\begin{lstlisting}
{
  public Main();
    descriptor: ()V
    flags: (0x0001) ACC_PUBLIC
    Code:
      stack=1, locals=1, args_size=1
         0: aload_0
         1: invokespecial #1                  // Method java/lang/Object."<init>":()V
         4: return
      LineNumberTable:
        line 1: 0
\end{lstlisting}

Metoda \texttt{main(String{[}{]}\ args)}:

\begin{lstlisting}
public static void main(java.lang.String[]);
descriptor: ([Ljava/lang/String;)V
flags: (0x0009) ACC_PUBLIC, ACC_STATIC
Code:
  stack=2, locals=1, args_size=1
     0: getstatic     #2                  // Field java/lang/System.out:Ljava/io/PrintStream;
     3: ldc           #3                  // String project1 - hello world
     5: invokevirtual #4                  // Method java/io/PrintStream.println:(Ljava/lang/String;)V
     8: invokestatic  #5                  // Method foo:()V
    11: return
  LineNumberTable:
    line 3: 0
    line 4: 8
    line 5: 11
\end{lstlisting}

Metoda \texttt{foo()}:

\begin{lstlisting}
public static void foo();
descriptor: ()V
flags: (0x0009) ACC_PUBLIC, ACC_STATIC
Code:
  stack=2, locals=0, args_size=0
     0: getstatic     #2                  // Field java/lang/System.out:Ljava/io/PrintStream;
     3: ldc           #6                  // String project1 - foo()
     5: invokevirtual #4                  // Method java/io/PrintStream.println:(Ljava/lang/String;)V
     8: return
  LineNumberTable:
    line 8: 0
    line 9: 8
\end{lstlisting}
